pystlouisfed/__init__.py
pystlouisfed/alfred.py
pystlouisfed/client.py
pystlouisfed/enums.py
pystlouisfed/fraser.py
pystlouisfed/fredmaps.py
pystlouisfed/models.py
pystlouisfed-3.0.0.dist-info/LICENSE
pystlouisfed-3.0.0.dist-info/METADATA
pystlouisfed-3.0.0.dist-info/WHEEL
pystlouisfed-3.0.0.dist-info/top_level.txt
pystlouisfed-3.0.0.dist-info/RECORD
