Metadata-Version: 2.1
Name: pystlouisfed
Version: 3.0.0
Summary: Federal Reserve Bank of St. Louis - FRED, ALFRED, FRED Maps and FRASER.
Author-email: Tomas Koutek <66636b6f6666@gmail.com>
License: MIT
Project-URL: Documentation, https://tomaskoutek.github.io/pystlouisfed/
Project-URL: Source, https://github.com/TomasKoutek/pystlouisfed
Project-URL: Tracker, https://github.com/TomasKoutek/pystlouisfed/issues
Keywords: economics,API,financial,FRED,ALFRED,FRASER,FRED Maps,stlouisfed,trading,algotrading
Classifier: Development Status :: 3 - Alpha
Classifier: Intended Audience :: Science/Research
Classifier: Intended Audience :: Developers
Classifier: Intended Audience :: Financial and Insurance Industry
Classifier: Operating System :: OS Independent
Classifier: Topic :: Software Development :: Libraries :: Python Modules
Classifier: Topic :: Internet :: WWW/HTTP
Classifier: Natural Language :: English
Classifier: Topic :: Office/Business :: Financial
Classifier: Topic :: Office/Business :: Financial :: Investment
Classifier: Intended Audience :: Education
Classifier: Topic :: Scientific/Engineering
Classifier: Topic :: Scientific/Engineering :: Information Analysis
Classifier: Programming Language :: Python :: 3.9
Classifier: Programming Language :: Python :: 3.10
Classifier: Programming Language :: Python :: 3.11
Requires-Python: >=3.9
License-File: LICENSE
Requires-Dist: pandas >1.0.0
Requires-Dist: geopandas
Requires-Dist: requests
Requires-Dist: rush
Requires-Dist: sickle
Requires-Dist: numpy
Provides-Extra: dev
Requires-Dist: ruff ; extra == 'dev'
Requires-Dist: sphinx ; extra == 'dev'
Requires-Dist: sphinx-rtd-theme ; extra == 'dev'
Requires-Dist: build ; extra == 'dev'
Requires-Dist: twine ; extra == 'dev'
